{"type":"header","name":"Header Group","sections":{"announcement-bar":{"type":"announcement-bar","blocks":{"60fe30b1-fa66-4bd9-9d3f-21fc97aa738c":{"type":"announcement","settings":{"text":"<p>All orders placed by May 30th will be delivered before Eid.<\/p>","btn_color":"#f84248","btn_border_color":"#ffffff","btn_bg_color":"#ffffff","btn_bg_color_gradient":""}}},"block_order":["60fe30b1-fa66-4bd9-9d3f-21fc97aa738c"],"disabled":true,"settings":{"layout":"scroll","enable_close":false,"color_text":"#ffffff","bg_color_text":"#232323","bg_color_text_gradient":"","font_size_text":12,"font_style_text":"normal","font_weight_text":"500","arrow_active":false,"content_max_width":38,"padding_top":0,"padding_top_tablet":0,"padding_top_mobile":0,"padding_bottom":0,"padding_bottom_tablet":0,"padding_bottom_mobile":0}},"9c03747e-b054-4db8-8194-5a35c71f82ca":{"type":"header-navigation-plain","blocks":{"sections--14682829619277__9c03747e-b054-4db8-8194-5a35c71f82ca-1680876693acfad79f-0":{"type":"logo","settings":{"logo_position":"always","logo":"shopify:\/\/shop_images\/chinyere-logo_1_4dac5727-89e6-4e26-93dc-68a733b26107.png","logo_width":155,"logo_width_fixed":100,"logo_text":"","logo_font_size":20,"logo_font_weight":"900","logo_text_transform":"uppercase","logo_color":"#ffffff"}},"sections--14682829619277__9c03747e-b054-4db8-8194-5a35c71f82ca-1680876693acfad79f-1":{"type":"main_menu","settings":{"menu":"manu-2025","menu_top_spacing":11,"menu_bottom_spacing":12,"grid_gap_menu_item":20,"alignment":"center","bg_mega_menu":"#ffffff","bg_mega_menu_gradient":"","lv_1_color":"#000000","lv_1_color_hover":"#000000","lv_2_color":"#232323","lv_2_color_hover":"#232323","lv_3_color":"#3c3c3c","lv_3_color_hover":"#3c3c3c","sale_item_1":"ELLA 30% OFF","sale_item_2":"","sale_item_3":"","sale_item_color":"#ff002c","label_position":"none","show_label_blink":true,"new_label_1":"","new_label_2":"Wishlist","new_label_3":"Home 21 - Yoga, Home 22 - Eyes Wears, Home 23 - Plant+ Garden, Home 24 - Bicycle, Mobile Sticky Toolbar, Home 25 - Swimwear 2, Sticky Promotion, Marquee Function, Home 26 - Bagratica, Section Groups, Home 27 - Men Fashion 02, Scroll Section","new_label_color":"#ffffff","new_label_bg":"#06bfe2","new_label_bg_gradient":"","sale_label_1":"30% Off","sale_label_2":"","sale_label_3":"","sale_label_color":"#ffffff","sale_label_bg":"#ff1a00","sale_label_bg_gradient":"","hot_label_1":"","hot_label_2":"RTL Layout, Store Locator","hot_label_3":"Bundle - Upsell, Variant Image Grouped, Home 02 - Trendy Style, Home 04 - High Fashion, Home 06 - SuperMarket, Home 15 - Automotive 2, Home 09 - Pet Supplies, Different Mobile Menu, Custom Options, Variant Metafield, Notify Me (Out Of Stock), Color Comparison, Product Combo","hot_label_color":"#ffffff","hot_label_bg":"#ffbb49","hot_label_bg_gradient":""}},"sections--14682829619277__9c03747e-b054-4db8-8194-5a35c71f82ca-1680876693acfad79f-2":{"type":"header_icons","settings":{"show_language_currency":false,"show_search":true,"show_customer":false,"show_wishlist":true,"show_wishlist_number":false,"show_cart":true,"text_font_size":14,"show_language_currency_sticky":false,"show_search_sticky":true,"show_customer_sticky":false,"show_wishlist_sticky":true,"show_cart_sticky":true,"cart_icon":"1","header_icons_color":"#000000","header_icons_color_hover":"#000000","header_icons_border_color":"rgba(0,0,0,0)","header_icons_border_sticky_color":"#ffffff","cart_count_bubble_color":"#ffffff","cart_count_bubble_bg":"#000000","cart_count_bubble_bg_gradient":"","wishlist_color_item":"#ffffff","wishlist_bg_item":"#232323"}},"d3131109-9329-42fa-bbb5-d25d01fd698b":{"type":"megamenu_style_1","settings":{"layout_block":"custom_width","header_custom_width_size":1200,"item":"new in","column":3,"show_banner_1":true,"banner_url_1":"shopify:\/\/collections\/blazero","show_product":true,"product_title":"Featured Products","product_collection":"naminos-dementus-a-dincidunto-5"}},"0e4cbbf3-fe5e-4e10-a837-c7651f114767":{"type":"megamenu_style_2","settings":{"layout_block":"custom_width","header_custom_width_size":1200,"item":"trend","column":3,"show_banner_1":true,"banner_url_1":"shopify:\/\/collections\/congue","show_banner_2":true,"banner_url_2":"shopify:\/\/collections\/cosmopolis","show_banner_3":true,"banner_url_3":"shopify:\/\/collections\/cosmopolitan"}},"4d022900-5ec2-41b0-89c1-edea75a13c28":{"type":"megamenu_style_3","settings":{"layout_block":"custom_width","header_custom_width_size":1200,"mega_tyle":"style1","item":"collections","column":5,"show_banner_1":true,"banner_url_1":"shopify:\/\/products\/dempus-lortis-cosmo-sapiendo","show_banner_2":true,"banner_url_2":"shopify:\/\/products\/dempus-lortis-cosmo-sapiendo-1","show_banner_3":true,"banner_url_3":"shopify:\/\/products\/dempus-lortis-cosmo-sapiendo-2","show_banner_4":true,"banner_url_4":"shopify:\/\/products\/dempus-lortis-cosmo-sapiendo-3","show_banner_5":true,"banner_url_5":"shopify:\/\/products\/dempus-an-lortis-tempus-sapiendos"}},"23b6fa6d-4f30-4a97-8dc1-2c516f8a7f0e":{"type":"megamenu_style_1","settings":{"layout_block":"custom_width","header_custom_width_size":1200,"item":"demo","column":5,"show_banner_1":false,"banner_url_1":"shopify:\/\/products\/dempus-lortis-cosmo-sapiendo-4","show_product":false,"product_title":"On Sale Products","product_collection":"dempus-an-lortis-tempus-sapiendos"}},"3d2520ed-30fc-4694-a7bd-8479ad2d6892":{"type":"megamenu_style_1","settings":{"layout_block":"custom_width","header_custom_width_size":1400,"item":"Theme Demo","column":5,"show_banner_1":false,"banner_url_1":"","show_product":false,"product_title":"Featured Products","product_collection":""}},"01014ccc-ffe5-4c78-b814-da3ff7d8b45c":{"type":"megamenu_style_1","settings":{"layout_block":"custom_width","header_custom_width_size":1200,"item":"Shop","column":4,"show_banner_1":false,"banner_url_1":"","show_product":false,"product_title":"Featured Products","product_collection":""}},"ec0f7e9f-1012-463e-a1fd-f9225f7f1cc3":{"type":"megamenu_style_1","settings":{"layout_block":"custom_width","header_custom_width_size":1400,"item":"Product","column":5,"show_banner_1":false,"banner_url_1":"","show_product":false,"product_title":"Featured Products","product_collection":""}}},"block_order":["sections--14682829619277__9c03747e-b054-4db8-8194-5a35c71f82ca-1680876693acfad79f-0","sections--14682829619277__9c03747e-b054-4db8-8194-5a35c71f82ca-1680876693acfad79f-1","sections--14682829619277__9c03747e-b054-4db8-8194-5a35c71f82ca-1680876693acfad79f-2","d3131109-9329-42fa-bbb5-d25d01fd698b","0e4cbbf3-fe5e-4e10-a837-c7651f114767","4d022900-5ec2-41b0-89c1-edea75a13c28","23b6fa6d-4f30-4a97-8dc1-2c516f8a7f0e","3d2520ed-30fc-4694-a7bd-8479ad2d6892","01014ccc-ffe5-4c78-b814-da3ff7d8b45c","ec0f7e9f-1012-463e-a1fd-f9225f7f1cc3"],"disabled":true,"settings":{"container":"full","padding_full_width":15,"header_navigation_bg":"#ffffff","header_navigation_bg_gradient":"","sticky_header_type":"always","sticky_header_width":"full","enable_transparent":false,"transparent_color":"#ffffff","transparent_color_hover":"#ffffff","border_color":"rgba(0,0,0,0)"}},"header-mobile":{"type":"header-mobile","blocks":{"7de2266e-0cd4-4fda-9f09-06f75a17f944":{"type":"menu","settings":{"color":"#232323","menu_tab_bg":"#000000"}},"wishlist_itVpRh":{"type":"wishlist","settings":{"color":"#ffffff","show_wishlist_number":false,"wishlist_color_item":"#ffffff","wishlist_bg_item":"#ffffff"}},"550fbd21-75fb-4051-9dee-77d91b5239f0":{"type":"logo","settings":{"logo_mobile":"shopify:\/\/shop_images\/chinyere-logo_1_4dac5727-89e6-4e26-93dc-68a733b26107.png","logo_width_mobile":100,"logo_text":"","logo_font_size":20,"logo_font_weight":"900","logo_text_transform":"uppercase","logo_color":"#232323","alignment":"center"}},"20dae707-64c0-4ea3-a05e-561cae9836d8":{"type":"customer","disabled":true,"settings":{"icon":"1","color":"#232323"}},"163e2cb5-14f2-4af6-9ac3-77193c082f53":{"type":"search","settings":{"icon":"1","popup_action":false,"color":"#232323"}},"633f9dae-3f65-4bda-9ca8-9d3e231aaf9d":{"type":"cart","settings":{"icon":"2","show_cart_count_bubble":true,"color":"#232323","color_bubble":"#ffffff","bg_bubble":"#232323"}}},"block_order":["7de2266e-0cd4-4fda-9f09-06f75a17f944","wishlist_itVpRh","550fbd21-75fb-4051-9dee-77d91b5239f0","20dae707-64c0-4ea3-a05e-561cae9836d8","163e2cb5-14f2-4af6-9ac3-77193c082f53","633f9dae-3f65-4bda-9ca8-9d3e231aaf9d"],"settings":{"background":"#ffffff","gradient":"","sticky_header_type":"on_scroll","enable_transparent":false,"transparent_color":"#ffffff","transparent_border_color":"","padding_top":0,"padding_bottom":0}},"header_navigation_compact_XeHEkM":{"type":"header-navigation-compact","blocks":{"logo_jhej6U":{"type":"logo","settings":{"logo_position":"always","logo":"shopify:\/\/shop_images\/chinyere-logo_1_4dac5727-89e6-4e26-93dc-68a733b26107.png","logo_width":130,"logo_width_fixed":100,"logo_text":"","logo_font_size":20,"logo_font_weight":"900","logo_text_transform":"uppercase","logo_color":"#000000"}},"main_menu_YaLWTG":{"type":"main_menu","settings":{"menu":"manu-2025","menu_top_spacing":20,"menu_bottom_spacing":20,"grid_gap_menu_item":14,"alignment":"center","bg_mega_menu":"#ffffff","bg_mega_menu_gradient":"","lv_1_color":"#000000","lv_1_color_hover":"#000000","lv_2_color":"#000000","lv_2_color_hover":"#000000","lv_3_color":"#000000","lv_3_color_hover":"#000000","sale_item_1":"","sale_item_2":"","sale_item_3":"","sale_item_color":"#d12442","label_position":"main_menu","show_label_blink":false,"new_label_1":"","new_label_2":"","new_label_3":"","new_label_color":"#ffffff","new_label_bg":"#bae4ed","new_label_bg_gradient":"","sale_label_1":"","sale_label_2":"","sale_label_3":"","sale_label_color":"#ffffff","sale_label_bg":"#d12442","sale_label_bg_gradient":"","hot_label_1":"","hot_label_2":"","hot_label_3":"","hot_label_color":"#ffffff","hot_label_bg":"#fff993","hot_label_bg_gradient":""}},"header_icons_ixdaNJ":{"type":"header_icons","settings":{"show_language_currency":false,"show_search":true,"show_customer":false,"show_wishlist":false,"show_wishlist_number":false,"show_cart":true,"text_font_size":12,"show_language_currency_sticky":false,"show_search_sticky":true,"show_customer_sticky":false,"show_wishlist_sticky":false,"show_cart_sticky":true,"header_icons_color":"#202020","header_icons_color_hover":"#202020","search_border_color":"#e6e6e6","search_dropdown_bg":"#eaeaea","search_dropdown_bg_gradient":"","search_dropdown_color":"#232323","search_dropdown_placeholder_color":"#bcbcbc","search_dropdown_icon_color":"#232323","cart_count_bubble_color":"#ffffff","cart_count_bubble_bg":"#232323","cart_count_bubble_bg_gradient":"","wishlist_color_item":"#ffffff","wishlist_bg_item":"#232323"}}},"block_order":["logo_jhej6U","main_menu_YaLWTG","header_icons_ixdaNJ"],"custom_css":[".header__inline-menu .menu-lv-item:first-parent .text {color: indianred; animation: blink 1s infinite;}",".header__inline-menu .list-menu--inline > li:nth-child(6) .menu-lv-1__action .text {color: darkred; animation: blink 1.5s infinite;}",".header__inline-menu .menu-lv-item .text {font-family: , sans-serif; font-weight: normal; font-style: normal;}"],"settings":{"container":"full","padding_full_width":15,"sticky_header_type":"always","sticky_header_width":"full","header_navigation_bg":"#ffffff","header_navigation_bg_gradient":"","header_navigation_border_top":"#e6e6e6","header_navigation_border_bottom":"#e6e6e6"}},"header_navigation_basic_JTBKzn":{"type":"header-navigation-basic","blocks":{"main_menu_8BgGJy":{"type":"main_menu","settings":{"menu":"main-menu","menu_top_spacing":17,"menu_bottom_spacing":17,"grid_gap_menu_item":12,"alignment":"left","bg_mega_menu":"#ffffff","bg_mega_menu_gradient":"","lv_1_color":"#26292d","lv_1_color_hover":"#26292d","lv_2_color":"#232323","lv_2_color_hover":"#232323","lv_3_color":"#3c3c3c","lv_3_color_hover":"#3c3c3c","sale_item_1":"","sale_item_2":"","sale_item_3":"","sale_item_color":"#d12442","label_position":"main_menu","show_label_blink":false,"new_label_1":"","new_label_2":"","new_label_3":"","new_label_color":"#ffffff","new_label_bg":"#4fb7d0","new_label_bg_gradient":"","sale_label_1":"","sale_label_2":"","sale_label_3":"","sale_label_color":"#ffffff","sale_label_bg":"#d12442","sale_label_bg_gradient":"","hot_label_1":"","hot_label_2":"","hot_label_3":"","hot_label_color":"#ffffff","hot_label_bg":"#fff993","hot_label_bg_gradient":""}},"logo_GxmeKp":{"type":"logo","settings":{"logo_position":"always","logo_width":70,"logo_width_fixed":100,"logo_text":"","logo_font_size":20,"logo_font_weight":"900","logo_text_transform":"uppercase","logo_color":"#000000"}},"header_icons_TweKXq":{"type":"header_icons","settings":{"menu_custom":"","show_wishlist":true,"show_wishlist_number":false,"show_customer":true,"show_search":true,"show_language_currency":true,"show_cart":true,"text_font_size":14,"show_wishlist_sticky":true,"show_customer_sticky":true,"show_search_sticky":true,"show_language_currency_sticky":false,"show_cart_sticky":false,"header_icons_color":"#26292d","header_icons_color_hover":"#26292d","cart_count_bubble_color":"#232323","cart_count_bubble_bg":"#ddbdb0","cart_count_bubble_bg_gradient":"","wishlist_color_item":"#ffffff","wishlist_bg_item":"#232323"}}},"block_order":["main_menu_8BgGJy","logo_GxmeKp","header_icons_TweKXq"],"disabled":true,"settings":{"container":"1170","padding_full_width":0,"header_navigation_bg":"#ffffff","header_navigation_bg_gradient":"","sticky_header_type":"on_scroll","sticky_header_width":"default"}}},"order":["announcement-bar","9c03747e-b054-4db8-8194-5a35c71f82ca","header-mobile","header_navigation_compact_XeHEkM","header_navigation_basic_JTBKzn"]}